tubeharvest/__init__.py
tubeharvest/__main__.py
tubeharvest/cli/__init__.py
tubeharvest/cli/interactive.py
tubeharvest/cli/main.py
tubeharvest/config/__init__.py
tubeharvest/config/settings.py
tubeharvest/core/__init__.py
tubeharvest/core/downloader.py
tubeharvest/core/utils.py
tubeharvest/ui/__init__.py
tubeharvest/ui/console.py
tubeharvest-2.0.0.dist-info/licenses/LICENSE
tubeharvest-2.0.0.dist-info/METADATA
tubeharvest-2.0.0.dist-info/WHEEL
tubeharvest-2.0.0.dist-info/entry_points.txt
tubeharvest-2.0.0.dist-info/top_level.txt
tubeharvest-2.0.0.dist-info/RECORD
