Metadata-Version: 2.4
Name: tubeharvest
Version: 2.0.0
Summary: A comprehensive YouTube downloader with beautiful interactive console interface
Author-email: TubeHarvest Team <contact@tubeharvest.com>
License-Expression: MIT
Project-URL: Homepage, https://github.com/msadeqsirjani/TubeHarvest
Project-URL: Repository, https://github.com/msadeqsirjani/TubeHarvest.git
Project-URL: Documentation, https://github.com/msadeqsirjani/TubeHarvest/wiki
Project-URL: Bug Tracker, https://github.com/msadeqsirjani/TubeHarvest/issues
Keywords: youtube,downloader,video,audio,playlist,cli,terminal
Classifier: Development Status :: 4 - Beta
Classifier: Intended Audience :: End Users/Desktop
Classifier: Operating System :: OS Independent
Classifier: Programming Language :: Python :: 3
Classifier: Programming Language :: Python :: 3.8
Classifier: Programming Language :: Python :: 3.9
Classifier: Programming Language :: Python :: 3.10
Classifier: Programming Language :: Python :: 3.11
Classifier: Programming Language :: Python :: 3.12
Classifier: Topic :: Multimedia :: Video
Classifier: Topic :: Internet :: WWW/HTTP
Classifier: Environment :: Console
Requires-Python: >=3.8
License-File: LICENSE
Requires-Dist: yt-dlp>=2023.3.4
Requires-Dist: tqdm>=4.65.0
Requires-Dist: requests>=2.28.2
Requires-Dist: python-ffmpeg-video-streaming>=0.1.15
Requires-Dist: colorama>=0.4.6
Requires-Dist: rich>=13.7.0
Requires-Dist: prompt-toolkit>=3.0.36
Requires-Dist: click>=8.1.7
Requires-Dist: inquirer>=3.1.3
Provides-Extra: dev
Requires-Dist: pytest>=7.4.0; extra == "dev"
Requires-Dist: pytest-cov>=4.1.0; extra == "dev"
Requires-Dist: pytest-mock>=3.11.0; extra == "dev"
Requires-Dist: pytest-xdist>=3.3.0; extra == "dev"
Requires-Dist: black>=23.7.0; extra == "dev"
Requires-Dist: flake8>=6.0.0; extra == "dev"
Requires-Dist: mypy>=1.5.0; extra == "dev"
Requires-Dist: isort>=5.12.0; extra == "dev"
Requires-Dist: pre-commit>=3.3.0; extra == "dev"
Requires-Dist: bandit>=1.7.5; extra == "dev"
Requires-Dist: safety>=2.3.0; extra == "dev"
Requires-Dist: ipython>=8.14.0; extra == "dev"
Requires-Dist: ipdb>=0.13.0; extra == "dev"
Requires-Dist: tox>=4.6.0; extra == "dev"
Requires-Dist: build>=0.10.0; extra == "dev"
Requires-Dist: twine>=4.0.0; extra == "dev"
Provides-Extra: test
Requires-Dist: pytest>=7.4.0; extra == "test"
Requires-Dist: pytest-cov>=4.1.0; extra == "test"
Requires-Dist: pytest-mock>=3.11.0; extra == "test"
Requires-Dist: pytest-xdist>=3.3.0; extra == "test"
Requires-Dist: coverage>=7.3.0; extra == "test"
Provides-Extra: docs
Requires-Dist: sphinx>=7.1.0; extra == "docs"
Requires-Dist: sphinx-rtd-theme>=1.3.0; extra == "docs"
Requires-Dist: mkdocs>=1.5.0; extra == "docs"
Requires-Dist: mkdocs-material>=9.1.0; extra == "docs"
Requires-Dist: myst-parser>=2.0.0; extra == "docs"
Dynamic: license-file
